Workbook

Sheet 0.1g PET, 2H
D3: Components | E3: Molar mass(g/mol) | F3: Boiling point(°C) | K3: Experimental Condition | M3: 0.1g PET, 0.5M PMA, 10ml(1M H2SO4 : DMSO = 1:1 v/v)
D4: PMA | E4: 1825.25 | F4: -
D5: H2SO4 | E5: 98.08 | F5: 337
D6: DMSO | E6: 78.13 | F6: 189 | N6: Reaction time(1Batch, hour) | O6: 2 | U6: Scaling factor | V6: 0.6 | AA6: Scaling factor | AB6: 0.6
D7: H2O | E7: 18.016 | F7: 100 | L7: Material | M7: Experimental Flow rate(g) | N7: Scale-up Flow rate(kg/2h) | O7: Scale-up Flow rate(kg/y) | R7: CAPEX (Equipment) | U7: CEPCI(2016) | V7: 541.7 | Y7: CAPEX (Equipment) | AA7: CEPCI(2016) | AB7: 541.7
D8: TPA | E8: 166.13 | F8: - | K8: Input | L8: PET | M8: =M19 -> 0.1 | N8: 1000 | O8: =N8*(24/$O$6)*365*$L$59 -> 3504000 | U8: CEPCI(2023) | V8: 800.8 | AA8: CEPCI(2023) | AB8: 800.8
D9: FA | E9: 46.03 | F9: 100.8 | L9: PMA | M9: =0.5/1000*10*E4 -> 9.12625 | N9: =M9*($N$8/$M$8) -> 91262.5 | O9: =N9 -> 91262.5 | R9: Equipment | S9: Installation Factor | T9: Capital Cost(2016$, 6.25 ton PET) | V9: Capital Cost(2023$, 1 ton PET) | Y9: Equipment | Z9: Capital Cost(2023$, 1 ton PET) | AA9: Capital Cost(2023$, 5 ton PET) | AB9: Capital Cost(2023$, 10 ton PET)
D10: H2 | E10: 2.016 | F10: -252.9 | L10: H2SO4 | M10: =5/1000*E5 -> 0.4904 | N10: =M10*($N$8/$M$8) -> 4904 | O10: =N10 -> 4904 | T10: Equipment Cost | U10: Installed Cost | V10: Installed Cost | Z10: Installed Cost | AA10: Installed Cost | AB10: Installed Cost
L11: DMSO | M11: =5*E15 -> 5.5 | N11: =M11*($N$8/$M$8) -> 55000 | O11: =N11+N11*(100-L63)*(24/O6)*365*L59 -> 247720 | R11: Feedstock Pretreatment | Y11: Feedstock Pretreatment
L12: H2O | M12: =5*E14-M10 -> 4.8096 | N12: =M12*($N$8/$M$8) -> 48096 | O12: =N12*(24/$O$6)*365*$L$59 -> 1.6852838e+08 | R12: Conveyor transfer system | S12: 1.7 | T12: 3933582 | U12: =S12*T12 -> 6687089.4 | V12: =U12*(1/6.25)^($V$6)*($V$8/$V$7) -> 3292110.1 | Y12: Conveyor transfer system | Z12: =V12 -> 3292110.1 | AA12: =Z12*(5/1)^$AB$6 -> 8646818.6 | AB12: =Z12*(10/1)^$AB$6 -> 13106126
D13: Density(g/mL, 25°C) | K13: Output | L13: TPA | M13: =$M$8*N20 -> 0.0863876 | N13: =M13*($N$8/$M$8) -> 863.876 | O13: =N13*(24/$O$6)*365*$L$59 -> 3027021.5 | R13: Truck dumper package | S13: 1.7 | T13: 224887 | U13: =S13*T13 -> 382307.9 | V13: =U13*(1/6.25)^($V$6)*($V$8/$V$7) -> 188213.38 | Y13: Truck dumper package | Z13: =V13 -> 188213.38 | AA13: =Z13*(5/1)^$AB$6 -> 494347.67 | AB13: =Z13*(10/1)^$AB$6 -> 749290.96
D14: 1M H2SO4 | E14: 1.06 | L14: FA | M14: =$M$8*N21 -> 0.0405064 | N14: =M14*($N$8/$M$8) -> 405.064 | O14: =N14*(24/$O$6)*365*$L$59 -> 1419344.3 | R14: Dust collection system | S14: 1.7 | T14: 56872 | U14: =S14*T14 -> 96682.4 | V14: =U14*(1/6.25)^($V$6)*($V$8/$V$7) -> 47597.555 | Y14: Dust collection system | Z14: =V14 -> 47597.555 | AA14: =Z14*(5/1)^$AB$6 -> 125016.3 | AB14: =Z14*(10/1)^$AB$6 -> 189489.28
D15: DMSO | E15: 1.1 | L15: H2 | M15: =$M$8*N22 -> 0.00532224 | N15: =M15*($N$8/$M$8) -> 53.2224 | O15: =N15*(24/$O$6)*365*$L$59 -> 186491.29 | R15: Feedstock storage dome | S15: 1.7 | T15: 711158 | U15: =S15*T15 -> 1208968.6 | V15: =U15*(1/6.25)^($V$6)*($V$8/$V$7) -> 595185.36 | Y15: Feedstock storage dome | Z15: =V15 -> 595185.36 | AA15: =Z15*(5/1)^$AB$6 -> 1563270.9 | AB15: =Z15*(10/1)^$AB$6 -> 2369475.6
R16: Shredder | S16: 1.7 | T16: 210000 | U16: =S16*T16 -> 357000 | V16: =U16*(1/6.25)^($V$6)*($V$8/$V$7) -> 175754.09 | Y16: Shredder | Z16: =V16 -> 175754.09 | AA16: =Z16*(5/1)^$AB$6 -> 461623 | AB16: =Z16*(10/1)^$AB$6 -> 699689.63
R17: Extruder | S17: 1.7 | T17: 2409639 | U17: =S17*T17 -> 4096386.3 | V17: =U17*(1/6.25)^($V$6)*($V$8/$V$7) -> 2016685.3 | Y17: Extruder | Z17: =V17 -> 2016685.3 | AA17: =Z17*(5/1)^$AB$6 -> 5296879.9 | AB17: =Z17*(10/1)^$AB$6 -> 8028568.6
D18: Components | E18: Cp(J/g·°C) | F18: ΔHvap(J/g) | K18: Feedstock & Product | L18: Mole(mol) | M18: Mass(g) | N18: Yield | R18: Microgranulator | S18: 1.7 | T18: 674295 | U18: =S18*T18 -> 1146301.5 | V18: =U18*(1/6.25)^($V$6)*($V$8/$V$7) -> 564333.82 | Y18: Microgranulator | Z18: =V18 -> 564333.82 | AA18: =Z18*(5/1)^$AB$6 -> 1482238.5 | AB18: =Z18*(10/1)^$AB$6 -> 2246653.4
D19: H2SO4 | E19: 1.34 | F19: 570.96 | K19: Input PET | L19: - | M19: 0.1 | N19: - | R19: Feedstock Pretreatment total($) | T19: =SUM(T12:T18) -> 8220433 | U19: =SUM(U12:U18) -> 13974736 | V19: =SUM(V12:V18) -> 6879879.5 | Y19: Feedstock Pretreatment total($) | Z19: =V19 -> 6879879.5 | AA19: =Z19*(5/1)^$AB$6 -> 18070195 | AB19: =Z19*(10/1)^$AB$6 -> 27389294
D20: DMSO | E20: 1.91 | F20: 677.08 | K20: Output TPA | L20: =0.00052 -> 0.00052 | M20: =L20*E8 -> 0.0863876 | N20: =M20/$M$19 -> 0.863876 | R20: PET Depolymerization | Y20: PET Depolymerization
D21: H2O | E21: 4.18 | F21: 2256.45 | K21: Output FA | L21: 0.00088 | M21: =L21*E9 -> 0.0405064 | N21: =M21/$M$19 -> 0.405064 | R21: Small particle conveyor | S21: 1 | T21: 820543 | U21: =S21*T21 -> 820543 | V21: =U21*(1/6.25)^($V$6)*($V$8/$V$7) -> 403960.19 | Y21: Small particle conveyor | Z21: =V21 -> 403960.19 | AA21: =Z21*(5/1)^$AB$6 -> 1061012.7 | AB21: =Z21*(10/1)^$AB$6 -> 1608194.5
D22: FA | E22: 2.15 | F22: 1005.9 | K22: Output H2 | L22: =3*L21 -> 0.00264 | M22: =L22*E10 -> 0.00532224 | N22: =M22/$M$19 -> 0.0532224 | R22: PMA storage and transfer | S22: 1.97 | T22: 294648 | U22: =S22*T22 -> 580456.56 | V22: =U22*(1/6.25)^($V$6)*($V$8/$V$7) -> 285763.62 | Y22: PMA storage and transfer | Z22: =V22 -> 285763.62 | AA22: =Z22*(5/1)^$AB$6 -> 750566.1 | AB22: =Z22*(10/1)^$AB$6 -> 1137645.5
R23: Water recirculation pump | S23: 2.3 | T23: 6417 | U23: =S23*T23 -> 14759.1 | V23: =U23*(1/6.25)^($V$6)*($V$8/$V$7) -> 7266.0284 | Y23: Water recirculation pump | Z23: =V23 -> 7266.0284 | AA23: =Z23*(5/1)^$AB$6 -> 19084.426 | AB23: =Z23*(10/1)^$AB$6 -> 28926.58
R24: Depolymerization reactor(7) | S24: 1.98 | T24: 5837187 | U24: =S24*T24 -> 11557630 | V24: =U24*(1/6.25)^($V$6)*($V$8/$V$7) -> 5689918.1 | Y24: Depolymerization reactor(7) | Z24: =V24 -> 5689918.1 | AA24: =Z24*(5/1)^$AB$6 -> 14944728 | AB24: =Z24*(10/1)^$AB$6 -> 22651972
D25: Heat duty calculation | E25: Heat duty(J) | F25: Heat duty(GJ) | K25: Electrolyzer | L25: H2 production | R25: Storage tanks | S25: 1.93 | T25: 102746 | U25: =S25*T25 -> 198299.78 | V25: =U25*(1/6.25)^($V$6)*($V$8/$V$7) -> 97624.641 | Y25: Storage tanks | Z25: =V25 -> 97624.641 | AA25: =Z25*(5/1)^$AB$6 -> 256413.83 | AB25: =Z25*(10/1)^$AB$6 -> 388650.7
D26: Reactor(100°C) → Electrolyzer(25°C) | E26: =-75*1000*($N$10*E19+$N$11*E20+$N$12*E21+$N$14*E22)-F21*N12-F22*N14 -> -2.3623948e+10 | F26: =E26/10^9 -> -23.623948 | K26: Current Density (mA/cm2) | L26: 125 | R26: Reactor effluent cooler | S26: 3.9 | T26: 21905 | U26: =S26*T26 -> 85429.5 | V26: =U26*(1/6.25)^($V$6)*($V$8/$V$7) -> 42057.658 | Y26: Reactor effluent cooler | Z26: =V26 -> 42057.658 | AA26: =Z26*(5/1)^$AB$6 -> 110465.61 | AB26: =Z26*(10/1)^$AB$6 -> 167434.55
D27: Electrolyzer(25°C) → Vessel(180°C) | E27: =155*1000*($N$10*E19+$N$11*E20+$N$12*E21+$N$14*E22)+F21*N12+F22*N14 -> 4.870663e+10 | F27: =E27/10^9 -> 48.70663 | K27: Cell Voltage(V) | L27: 1.2 | R27: Caustic storage and transfer | S27: 1.97 | T27: 138836 | U27: =S27*T27 -> 273506.92 | V27: =U27*(1/6.25)^($V$6)*($V$8/$V$7) -> 134649.75 | Y27: Caustic storage and transfer | Z27: =V27 -> 134649.75 | AA27: =Z27*(5/1)^$AB$6 -> 353661.3 | AB27: =Z27*(10/1)^$AB$6 -> 536050.29
D28: Vessel(180°C) → Reactor(100°C) | E28: =-80*1000*($N$10*E19+$N$11*E20) -> -8929708800 | F28: =E28/10^9 -> -8.9297088 | K28: Faradaic Efficiency(%) | L28: 0.95 | R28: PET Depolymerization total($) | T28: =SUM(T21:T27) -> 7222282 | U28: =SUM(U21:U27) -> 13530625 | V28: =SUM(V21:V27) -> 6661240 | Y28: PET Depolymerization total($) | Z28: =V28 -> 6661240 | AA28: =Z28*(5/1)^$AB$6 -> 17495932 | AB28: =Z28*(10/1)^$AB$6 -> 26518874
D29: Total Heat duty | E29: =SUM(E26:E28) -> 16152973408 | F29: =E29/10^9 -> 16.152973 | R29: TPA Filteration & Crystallization | Y29: TPA Filteration & Crystallization
R30: Solids filter package | S30: 1.74 | T30: 2250175 | U30: =S30*T30 -> 3915304.5 | V30: =U30*(1/6.25)^($V$6)*($V$8/$V$7) -> 1927537.2 | Y30: Solids filter package | Z30: =V30 -> 1927537.2 | AA30: =Z30*(5/1)^$AB$6 -> 5062730 | AB30: =Z30*(10/1)^$AB$6 -> 7673663.7
K31: Required Electrolyzer Area(m2) | L31: =(N15*1000/E10)*2*96485/(O6*3600*L28*L26*10) -> 595.83719 | R31: rTPA crystallizer | S31: 2.5 | T31: 2868818 | U31: =S31*T31 -> 7172045 | V31: =U31*(1/6.25)^($V$6)*($V$8/$V$7) -> 3530857.8 | Y31: rTPA crystallizer | Z31: =V31 -> 3530857.8 | AA31: =Z31*(5/1)^$AB$6 -> 9273896.1 | AB31: =Z31*(10/1)^$AB$6 -> 14056598
E32: Material Unit Prices | K32: Required Electrolysis Energy(kWh/y) | L32: =O15*L38 -> 5949072.1 | R32: rTPA centrifuge | S32: 2.3 | T32: 639362 | U32: =S32*T32 -> 1470532.6 | V32: =U32*(1/6.25)^($V$6)*($V$8/$V$7) -> 723955.51 | Y32: rTPA centrifuge | Z32: =V32 -> 723955.51 | AA32: =Z32*(5/1)^$AB$6 -> 1901489.3 | AB32: =Z32*(10/1)^$AB$6 -> 2882118.8
E33: Components | F33: Low Cost($/kg) | G33: High Cost($/kg) | H33: Ref | R33: rTPA crystals dryer | S33: 1.5 | T33: 923378 | U33: =S33*T33 -> 1385067 | V33: =U33*(1/6.25)^($V$6)*($V$8/$V$7) -> 681880.08 | Y33: rTPA crystals dryer | Z33: =V33 -> 681880.08 | AA33: =Z33*(5/1)^$AB$6 -> 1790977 | AB33: =Z33*(10/1)^$AB$6 -> 2714613.5
D34: Input | E34: Industrial PET | F34: 0.25 | G34: 0.4 | H34: ICIS 2024 | R34: TPA Filteration & Crystallization total($) | T34: =SUM(T30:T33) -> 6681733 | U34: =SUM(U30:U33) -> 13942949 | V34: =SUM(V30:V33) -> 6864230.5 | Y34: TPA Filteration & Crystallization total($) | Z34: =V34 -> 6864230.5 | AA34: =Z34*(5/1)^$AB$6 -> 18029092 | AB34: =Z34*(10/1)^$AB$6 -> 27326994
E35: Waste PET | F35: 0 | G35: 0.1 | H35: Recycling Market 2024 | K35: Assumptions | L35: Price | M35: Ref | R35: Electrolysis | Y35: Electrolysis
E36: Phosphomolybdic Acid(PMA) | F36: =0.01 -> 0.01 | G36: - | H36: Made-in-China | K36: Electrolyzer($/m^2) | L36: 10000 | M36: Nat Commun 12, 4679 (2021) | R36: Electrolyzer | S36: - | T36: - | U36: - | V36: =L31*L36 -> 5958371.9 | Y36: Electrolyzer | Z36: =V36 -> 5958371.9 | AA36: =Z36*(5/1)^$AB$6 -> 15649830 | AB36: =Z36*(10/1)^$AB$6 -> 23720706
E37: H2SO4 | F37: 0.037 | G37: - | H37: Made-in-China | K37: Electricity($/kWh) | L37: 0.0953 | M37: Kepco data | R37: H2 storage tank | S37: 1.3 | T37: 600000 | U37: =S37*T37 -> 780000 | V37: =U37*(1/6.25)^($V$6)*($V$8/$V$7) -> 384000.53 | Y37: H2 storage tank | Z37: =V37 -> 384000.53 | AA37: =Z37*(5/1)^$AB$6 -> 1008588.1 | AB37: =Z37*(10/1)^$AB$6 -> 1528733.6
E38: Dimethyl Sulfoxide(DMSO) | F38: 1.5 | G38: - | H38: Echemi | K38: H2 Electrolysis Energy(kWh/kg H2) | L38: 31.9 | M38: - | R38: Electrolysis total($) | T38: =SUM(T36:T37) -> 600000 | U38: =SUM(U36:U37) -> 780000 | V38: =SUM(V36:V37) -> 6342372.5 | Y38: Electrolysis total($) | Z38: =V38 -> 6342372.5 | AA38: =Z38*(5/1)^$AB$6 -> 16658418 | AB38: =Z38*(10/1)^$AB$6 -> 25249440
E39: H2O | F39: 0.00022 | G39: - | H39: Nat Commun 12, 4679 (2021) | K39: Reactor heating(100°C) Electricity($/ton PET) | L39: 17 | M39: - | R39: OSBL | Y39: OSBL
D40: Output | E40: Terephthalic Acid(TPA) | F40: 0.94 | G40: - | H40: - | K40: Mechanical Crushing Electricity($/ton PET) | L40: 13 | M40: - | R40: Outside battery limits capital(25% of ISBL) | T40: =SUM(T$19,T$28,T$34,T$38)*0.25 -> 5681112 | U40: =SUM(U$19,U$28,U$34,U$38)*0.25 -> 10557078 | V40: =SUM(V$19,V$28,V$34,V$38)*0.25 -> 6686930.6 | Y40: Outside battery limits capital(25% of ISBL) | Z40: =V40 -> 6686930.6 | AA40: =SUM(AA$19,AA$28,AA$34,AA$38)*0.25 -> 17563409 | AB40: =SUM(AB$19,AB$28,AB$34,AB$38)*0.25 -> 26621150
E41: Formic Acid(FA) | F41: 0.84 | G41: - | H41: - | K41: Total Catalyst & Membrane cost / Electrolyzer | L41: 0.05 | M41: Nat Commun 12, 4679 (2021) | R41: OSBL total($) | T41: =SUM(T40) -> 5681112 | U41: =SUM(U40) -> 10557078 | V41: =SUM(V40) -> 6686930.6 | Y41: OSBL total($) | Z41: =V41 -> 6686930.6 | AA41: =SUM(AA$19,AA$28,AA$34,AA$38)*0.25 -> 17563409 | AB41: =SUM(AB$19,AB$28,AB$34,AB$38)*0.25 -> 26621150
E42: H2 | F42: 8 | G42: - | H42: - | R42: Total($) | T42: =SUM(T19,T28,T34,T38,T41) -> 28405560 | U42: =SUM(U19,U28,U34,U38,U41) -> 52785388 | V42: =SUM(V19,V28,V34,V38,V41) -> 33434653 | Y42: Total($) | Z42: =SUM(Z19,Z28,Z34,Z38,Z41) -> 33434653 | AA42: =SUM(AA19,AA28,AA34,AA38,AA41) -> 87817046 | AB42: =SUM(AB19,AB28,AB34,AB38,AB41) -> 1.3310575e+08
R43: Annualized Capital Cost($/y) | T43: =V42*L58 -> 3546722.9 | Y43: Annualized Capital Cost($/y) | Z43: =Z42*$L$58 -> 3546722.9 | AA43: =AA42*$L$58 -> 9315566.2 | AB43: =AB42*$L$58 -> 14119758
K44: Heating Assumption | L44: Value | M44: Ref
K45: Medium pressure steam($/GJ) | L45: 4.77 | M45: Turton et al., Chem. Process Design, 5th ed. (2018)
K46: Total Heat duty(GJ) | L46: =F29 -> 16.152973 | M46: - | R46: CAPEX (Feedstock) | U46: CAPEX (Distillation)
K47: Heating cost($/ton PET) | L47: =L45*L46 -> 77.049683 | M47: - | Y47: CAPEX (Feedstock) | AD47: CAPEX (Distillation)
R48: Parameter | S48: Cost($/y) | U48: Parameter | V48: Cost($/y)
R49: PMA | S49: =N9*F36 -> 912.625 | U49: FA distillation | V49: =L52*O14 -> 125538.87 | Y49: Parameter | Z49: 1 ton PET Cost($/y) | AA49: 5 ton PET Cost($/y) | AB49: 10 ton PET Cost($/y) | AD49: Parameter | AE49: 1 ton PET Cost($/y) | AF49: 5 ton PET Cost($/y) | AG49: 10 ton PET Cost($/y)
K50: FA distillation Assumption | L50: Value | M50: Ref | R50: H2SO4 | S50: =N10*F37 -> 181.448 | U50: Total($/y) | V50: =SUM(V49:V49) -> 125538.87 | Y50: PMA | Z50: =S49 -> 912.625 | AA50: =Z50*5 -> 4563.125 | AB50: =Z50*10 -> 9126.25 | AD50: FA distillation | AE50: =V50 -> 125538.87 | AF50: =AE50*5 -> 627694.35 | AG50: =AE50*10 -> 1255388.7
K51: FA output concentration(wt%) | L51: =N14/(N14+N12)*100 -> 0.83516518 | R51: DMSO | S51: =N11*F38 -> 82500 | Y51: H2SO4 | Z51: =S50 -> 181.448 | AA51: =Z51*5 -> 907.24 | AB51: =Z51*10 -> 1814.48 | AD51: Total($/y) | AE51: =SUM(AE50:AE50) -> 125538.87 | AF51: =SUM(AF50:AF50) -> 627694.35 | AG51: =SUM(AG50:AG50) -> 1255388.7
K52: FA distillation CAPEX($/kg FA) | L52: 0.0884485 | M52: Ind. Eng. Chem. Res. 2021, 60, 5588-5599 | R52: Total($/y) | S52: =SUM(S49:S51) -> 83594.073 | Y52: DMSO | Z52: =S51 -> 82500 | AA52: =Z52*5 -> 412500 | AB52: =Z52*10 -> 825000
K53: FA distillation OPEX($/kg FA) | L53: 0.863293 | M53: Ind. Eng. Chem. Res. 2021, 60, 5588-5599 | Y53: Total($/y) | Z53: =SUM(Z50:Z52) -> 83594.073 | AA53: =SUM(AA50:AA52) -> 417970.36 | AB53: =SUM(AB50:AB52) -> 835940.73
R55: OPEX (Feedstock) | U55: OPEX (Distillation)
K56: Discount rate(%) | L56: 0.1 | M56: Joule 5, 2479-2503 (2021)
K57: Life time(y) | L57: 30 | M57: Joule 5, 2479-2503 (2021) | R57: Parameter | S57: Cost($/y) | U57: Parameter | V57: Cost($/y) | Y57: OPEX (Feedstock) | AD57: OPEX (Distillation)
K58: Capital recovery factor | L58: =(L56*(1+L56)^(L57))/(((1+L56)^(L57))-1) -> 0.10607925 | M58: - | R58: PET | S58: =O8*G35 -> 350400 | U58: FA distillation | V58: =L53*O14 -> 1225310
K59: Capacity Factor | L59: 0.8 | M59: Nat Commun 12, 4679 (2021) | R59: DMSO | S59: =L67*24*365*$L$59 -> 289080 | U59: Total($/y) | V59: =SUM(V58:V58) -> 1225310 | Y59: Parameter | Z59: 1 ton PET Cost($/y) | AA59: 5 ton PET Cost($/y) | AB59: 10 ton PET Cost($/y) | AD59: Parameter | AE59: 1 ton PET Cost($/y) | AF59: 5 ton PET Cost($/y) | AG59: 10 ton PET Cost($/y)
K60: Separation Electricity = Reactor Electricity | M60: Nano Lett. 24, 9768-9775 (2024) | R60: PMA | S60: =L68*24*365*$L$59 -> 0 | Y60: PET | Z60: =S58 -> 350400 | AA60: =Z60*5 -> 1752000 | AB60: =Z60*5 -> 1752000 | AD60: FA distillation | AE60: =V59 -> 1225310 | AF60: =AE60*5 -> 6126549.8 | AG60: =AE60*10 -> 12253100
K61: Maintenance cost per year / CAPEX | L61: 0.1 | M61: Nat Commun 12, 4679 (2021) | R61: H2SO4 | S61: =L69*24*365*$L$59 -> 0 | Y61: DMSO | Z61: =S59 -> 289080 | AA61: =Z61*5 -> 1445400 | AB61: =Z61*10 -> 2890800 | AD61: Total($/y) | AE61: =SUM(AE60:AE60) -> 1225310 | AF61: =SUM(AF60:AF60) -> 6126549.8 | AG61: =SUM(AG60:AG60) -> 12253100
K62: Operating cost per year / CAPEX | L62: 0.1 | M62: Nat Commun 12, 4679 (2021) | R62: H2O | S62: =L66*24*365*L59 -> 37076.244 | Y62: PMA | Z62: =S60 -> 0 | AA62: =Z62*5 -> 0 | AB62: =Z62*10 -> 0
K63: DMSO recovery(%) | L63: 99.999 | M63: - | R63: Total($/y) | S63: =SUM(S58:S62) -> 676556.24 | Y63: H2SO4 | Z63: =S61 -> 0 | AA63: =Z63*5 -> 0 | AB63: =Z63*10 -> 0
K64: PMA recovery(%) | L64: 100 | M64: - | Y64: H2O | Z64: =S62 -> 37076.244 | AA64: =Z64*5 -> 185381.22 | AB64: =Z64*10 -> 370762.44
K65: H2SO4 recovery(%) | L65: 100 | M65: - | Y65: Total($/y) | Z65: =SUM(Z60:Z64) -> 676556.24 | AA65: =SUM(AA60:AA64) -> 3382781.2 | AB65: =SUM(AB60:AB64) -> 5013562.4
K66: H2O makeup($/h) | L66: =N12*F39/O6 -> 5.29056 | M66: - | R66: OPEX (Utility) | U66: OPEX (Operation)
K67: DMSO makeup($/h) | L67: =(N11/O6)*(100-L63)*F38 -> 41.25 | M67: -
K68: PMA makeup($/h) | L68: =(N9/O6)*(100-L64)*F36 -> 0 | M68: - | R68: Parameter | S68: Cost($/y) | U68: Parameter | V68: Cost($/y) | Y68: OPEX (Utility) | AD68: OPEX (Operation)
K69: H2SO4 makeup($/h) | L69: =(N10/O6)*(100-L65)*F37 -> 0 | M69: - | R69: Electricity | S69: =L38*O15*L37 -> 566946.57 | U69: Maintenance | V69: =SUM($T$43+$S$52)*$L$61 -> 363031.69
R70: Heat | S70: =L47*O8/1000 -> 269982.09 | U70: Operation | V70: =SUM($T$43+$S$52)*$L$61 -> 363031.69 | Y70: Parameter | Z70: 1 ton PET Cost($/y) | AA70: 5 ton PET Cost($/y) | AB70: 10 ton PET Cost($/y) | AD70: Parameter | AE70: 1 ton PET Cost($/y) | AF70: 5 ton PET Cost($/y) | AG70: 10 ton PET Cost($/y)
R71: Mechanical crushing | S71: =L40*O8/1000 -> 45552 | U71: Total($/y) | V71: =SUM(V69:V70) -> 726063.39 | Y71: Electricity | Z71: =S69 -> 566946.57 | AA71: =Z71*5 -> 2834732.9 | AB71: =Z71*10 -> 5669465.7 | AD71: Maintenance | AE71: =V69 -> 363031.69 | AF71: =AE71*5 -> 1815158.5 | AG71: =AE71*10 -> 3630316.9
R72: Total($/y) | S72: =SUM(S69:S71) -> 882480.66 | Y72: Heat | Z72: =S70 -> 269982.09 | AA72: =Z72*5 -> 1349910.4 | AB72: =Z72*10 -> 2699820.9 | AD72: Operation | AE72: =V70 -> 363031.69 | AF72: =AE72*5 -> 1815158.5 | AG72: =AE72*10 -> 3630316.9
Y73: Mechanical crushing | Z73: =S71 -> 45552 | AA73: =Z73*5 -> 227760 | AB73: =Z73*10 -> 455520 | AD73: Total($/y) | AE73: =SUM(AE71:AE72) -> 726063.39 | AF73: =SUM(AF71:AF72) -> 3630316.9 | AG73: =SUM(AG71:AG72) -> 7260633.9
Y74: Total($/y) | Z74: =SUM(Z71:Z73) -> 882480.66 | AA74: =SUM(AA71:AA73) -> 4412403.3 | AB74: =SUM(AB71:AB73) -> 8824806.6
R75: Revenue | U75: Profit
R77: Parameter | S77: Cost($/y) | U77: CAPEX($/y) | V77: =T43+S52+V50 -> 3755855.8 | Y77: Revenue | AD77: Route3(FA, 2H) Profit
R78: TPA | S78: =O13*F40 -> 2845400.2 | U78: OPEX($/y) | V78: =S63+V59+S72+V71 -> 3510410.3 | AE78: 1 ton PET Cost($/y) | AF78: 5 ton PET Cost($/y) | AG78: 10 ton PET Cost($/y)
R79: FA | S79: =O14*F41 -> 1192249.2 | U79: Revenue($/y) | V79: =S81 -> 5529579.7 | Y79: Parameter | Z79: 1 ton PET Cost($/y) | AA79: 5 ton PET Cost($/y) | AB79: 10 ton PET Cost($/y) | AD79: CAPEX($/y) | AE79: =Z43+Z53+AE51 -> 3755855.8 | AF79: =AA43+AA53+AF51 -> 10361231 | AG79: =AB43+AB53+AG51 -> 16211087
R80: H2 | S80: =O15*F42 -> 1491930.3 | U80: Profit($/y) | V80: =V79-V77-V78 -> -1736686.4 | Y80: TPA | Z80: =S78 -> 2845400.2 | AA80: =Z80*5 -> 14227001 | AB80: =Z80*10 -> 28454002 | AD80: OPEX($/y) | AE80: =Z65+AE61+Z74+AE73 -> 3510410.3 | AF80: =AA65+AF61+AA74+AF73 -> 17552051 | AG80: =AB65+AG61+AB74+AG73 -> 33352103
R81: Total($/y) | S81: =SUM(S78:S80) -> 5529579.7 | Y81: FA | Z81: =S79 -> 1192249.2 | AA81: =Z81*5 -> 5961245.9 | AB81: =Z81*10 -> 11922492 | AD81: Revenue($/y) | AE81: =Z83 -> 5529579.7 | AF81: =AA83 -> 27647899 | AG81: =AB83 -> 55295797
Y82: H2 | Z82: =S80 -> 1491930.3 | AA82: =Z82*5 -> 7459651.6 | AB82: =Z82*10 -> 14919303 | AD82: Profit($/y) | AE82: =AE81-AE79-AE80 -> -1736686.4 | AF82: =AF81-AF79-AF80 -> -265383.71 | AG82: =AG81-AG79-AG80 -> 5732607
Y83: Total($/y) | Z83: =SUM(Z80:Z82) -> 5529579.7 | AA83: =SUM(AA80:AA82) -> 27647899 | AB83: =SUM(AB80:AB82) -> 55295797
Y86: Route3(FA, 2H) MSP of TPA | AD86: MSP of Other methods
Z87: PET 1ton | AA87: PET 5ton | AB87: PET 10ton | AD87: Glycolysis | AE87: 0.96 | AF87: ACS Sustainable Chem. Eng. 2023, 11, 965−978
Y88: $/kg TPA | Z88: =(AE79+AE80-SUM(Z81:Z82))/$O$13 -> 1.5137278 | AA88: =(AF79+AF80-SUM(AA81:AA82))/($O$13*5) -> 0.95753431 | AB88: =(AG79+AG80-SUM(AB81:AB82))/($O$13*10) -> 0.75061889 | AD88: Methanolysis | AE88: 1.05 | AF88: ACS Sustainable Chem. Eng. 2023, 11, 965−978
AD89: Enzymatic degradation | AE89: 1.93 | AF89: Joule 5, 2479–2503 (2021)
AE90: 2.18 | AF90: Green Chem., 2022, 24, 6531
Y91: Cost Breakdown(10 ton PET) | AE91: 2.01 | AF91: ACS Sustainable Chem. Eng. 2023, 11, 965−978
Z92: Value($/y) | AA92: Portion(%) | AD92: Solvent-based recycling | AE92: 0.87 | AF92: ACS Sustainable Chem. Eng. 2023, 11, 965−978
Y93: CAPEX | Z93: =SUM(AB43,AG51) -> 15375147 | AA93: =Z93/$Z$97*100 -> 31.021302 | AD93: Mechanical recycling | AE93: 0.54 | AF93: ACS Sustainable Chem. Eng. 2023, 11, 965−978
Y94: Feedstock Cost | Z94: =SUM(AB53,AB65) -> 5849503.2 | AA94: =Z94/$Z$97*100 -> 11.802112 | AD94: Virgin TPA | AE94: 1.14 | AF94: Chem. Eng. Journal 481 (2024) 148278
Y95: Utility Cost | Z95: =SUM(AB74) -> 8824806.6 | AA95: =Z95/$Z$97*100 -> 17.805163
Y96: OPEX | Z96: =SUM(AG61, AG73) -> 19513733 | AA96: =Z96/$Z$97*100 -> 39.371424
Y97: Total | Z97: =SUM(Z93:Z96) -> 49563190 | AA97: =Z97/$Z$97*100 -> 100
Y100: Cost Breakdown of sub items (10 ton PET) | AB100: Revenue Breakdown
Z101: Portion(%) | AC101: Portion(%)
Y102: Electricity | Z102: =AB71/Z97*100 -> 11.438864 | AB102: TPA | AC102: =AB80/$AB$83*100 -> 51.457803
Y103: Heat | Z103: =AB72/Z97*100 -> 5.4472299 | AB103: FA | AC103: =AB81/$AB$83*100 -> 21.561298
Y104: PMA | Z104: =AB50/Z97*100 -> 0.018413363 | AB104: H2 | AC104: =AB82/$AB$83*100 -> 26.980899
Y105: DMSO | Z105: =(AB52+AB61)/Z97*100 -> 7.4970961
Y108: Sensitivity Analysis (10 ton PET)
Z109: Value | AA109: MSP of TPA
Y110: DMSO recovery(%) | Z110: 99.999 | AA110: 0.75
...

Sheet TEA Summary
B2: PET Degradation Techno-Economic Analysis (TEA) Summary
B3: 0.1g PET, 0.5M PMA, 10ml (1M H₂SO₄ : DMSO = 1:1 v/v), 2H Reaction
B5: 1. Experimental Conditions & Scale-up
B7: Parameter | C7: Experimental (g) | D7: Scale-up (kg/2h) | E7: Annual (kg/y)
B8: PET (Input) | C8: ='0.1g PET, 2H'!M8 -> 0.1 | D8: ='0.1g PET, 2H'!N8 -> 1000 | E8: ='0.1g PET, 2H'!O8 -> 3504000
B9: PMA | C9: ='0.1g PET, 2H'!M9 -> 9.12625 | D9: ='0.1g PET, 2H'!N9 -> 91262.5 | E9: ='0.1g PET, 2H'!O9 -> 91262.5
B10: H₂SO₄ | C10: ='0.1g PET, 2H'!M10 -> 0.4904 | D10: ='0.1g PET, 2H'!N10 -> 4904 | E10: ='0.1g PET, 2H'!O10 -> 4904
B11: DMSO | C11: ='0.1g PET, 2H'!M11 -> 5.5 | D11: ='0.1g PET, 2H'!N11 -> 55000 | E11: ='0.1g PET, 2H'!O11 -> 247720
B12: H₂O | C12: ='0.1g PET, 2H'!M12 -> 4.8096 | D12: ='0.1g PET, 2H'!N12 -> 48096 | E12: ='0.1g PET, 2H'!O12 -> 1.6852838e+08
B13: TPA (Output) | C13: ='0.1g PET, 2H'!M13 -> 0.0863876 | D13: ='0.1g PET, 2H'!N13 -> 863.876 | E13: ='0.1g PET, 2H'!O13 -> 3027021.5
B14: FA (Output) | C14: ='0.1g PET, 2H'!M14 -> 0.0405064 | D14: ='0.1g PET, 2H'!N14 -> 405.064 | E14: ='0.1g PET, 2H'!O14 -> 1419344.3
B15: H₂ (Output) | C15: ='0.1g PET, 2H'!M15 -> 0.00532224 | D15: ='0.1g PET, 2H'!N15 -> 53.2224 | E15: ='0.1g PET, 2H'!O15 -> 186491.29
B17: 2. Key Assumptions
B19: Parameter | C19: Value | D19: Ref
B20: Reaction time (1 Batch) | C20: ='0.1g PET, 2H'!O6 -> 2
B21: Discount rate | C21: ='0.1g PET, 2H'!L56 -> 0.1 | D21: ='0.1g PET, 2H'!M56 -> Joule 5, 2479-2503 (2021)
B22: Lifetime | C22: ='0.1g PET, 2H'!L57 -> 30 | D22: ='0.1g PET, 2H'!M57 -> Joule 5, 2479-2503 (2021)
B23: Capital recovery factor | C23: ='0.1g PET, 2H'!L58 -> 0.10607925
B24: Capacity factor | C24: ='0.1g PET, 2H'!L59 -> 0.8 | D24: ='0.1g PET, 2H'!M59 -> Nat Commun 12, 4679 (2021)
B25: Scaling factor | C25: ='0.1g PET, 2H'!V6 -> 0.6
B26: CEPCI (2016 → 2023) | C26: 541.7 → 800.8
B27: Electrolyzer ($/m²) | C27: ='0.1g PET, 2H'!L36 -> 10000 | D27: ='0.1g PET, 2H'!M36 -> Nat Commun 12, 4679 (2021)
B28: Electricity ($/kWh) | C28: ='0.1g PET, 2H'!L37 -> 0.0953 | D28: ='0.1g PET, 2H'!M37 -> Kepco data
B29: DMSO recovery (%) | C29: ='0.1g PET, 2H'!L63 -> 99.999
B30: PMA recovery (%) | C30: ='0.1g PET, 2H'!L64 -> 100
B32: 3. CAPEX Summary (Equipment + Installation)
B34: Equipment Category | C34: 1 ton PET ($/y) | D34: 5 ton PET ($/y) | E34: 10 ton PET ($/y)
B35: Feedstock Pretreatment | C35: ='0.1g PET, 2H'!V19 -> 6879879.5 | D35: ='0.1g PET, 2H'!AA19 -> 18070195 | E35: ='0.1g PET, 2H'!AB19 -> 27389294
B36: PET Depolymerization | C36: ='0.1g PET, 2H'!V28 -> 6661240 | D36: ='0.1g PET, 2H'!AA28 -> 17495932 | E36: ='0.1g PET, 2H'!AB28 -> 26518874
B37: TPA Filtration & Crystallization | C37: ='0.1g PET, 2H'!V34 -> 6864230.5 | D37: ='0.1g PET, 2H'!AA34 -> 18029092 | E37: ='0.1g PET, 2H'!AB34 -> 27326994
B38: Electrolysis | C38: ='0.1g PET, 2H'!V38 -> 6342372.5 | D38: ='0.1g PET, 2H'!AA38 -> 16658418 | E38: ='0.1g PET, 2H'!AB38 -> 25249440
B39: OSBL (25% of ISBL) | C39: ='0.1g PET, 2H'!V41 -> 6686930.6 | D39: ='0.1g PET, 2H'!AA41 -> 17563409 | E39: ='0.1g PET, 2H'!AB41 -> 26621150
B40: Total Equipment CAPEX | C40: ='0.1g PET, 2H'!V42 -> 33434653 | D40: ='0.1g PET, 2H'!AA42 -> 87817046 | E40: ='0.1g PET, 2H'!AB42 -> 1.3310575e+08
B41: Annualized Equipment CAPEX | C41: ='0.1g PET, 2H'!Z43 -> 3546722.9 | D41: ='0.1g PET, 2H'!AA43 -> 9315566.2 | E41: ='0.1g PET, 2H'!AB43 -> 14119758
B43: Annualized CAPEX - Feedstock (Initial) | C43: ='0.1g PET, 2H'!Z53 -> 83594.073 | D43: ='0.1g PET, 2H'!AA53 -> 417970.36 | E43: ='0.1g PET, 2H'!AB53 -> 835940.73
B44: Annualized CAPEX - FA Distillation | C44: ='0.1g PET, 2H'!AE51 -> 125538.87 | D44: ='0.1g PET, 2H'!AF51 -> 627694.35 | E44: ='0.1g PET, 2H'!AG51 -> 1255388.7
B45: Total Annualized CAPEX | C45: =C41+C43+C44 -> 3755855.8 | D45: =D41+D43+D44 -> 10361231 | E45: =E41+E43+E44 -> 16211087
B47: 4. OPEX Summary (Annual Operating Cost)
B49: OPEX Category | C49: 1 ton PET ($/y) | D49: 5 ton PET ($/y) | E49: 10 ton PET ($/y)
B50: Feedstock - PET | C50: ='0.1g PET, 2H'!Z60 -> 350400 | D50: ='0.1g PET, 2H'!AA60 -> 1752000 | E50: ='0.1g PET, 2H'!AB60 -> 1752000
B51: Feedstock - DMSO makeup | C51: ='0.1g PET, 2H'!Z61 -> 289080 | D51: ='0.1g PET, 2H'!AA61 -> 1445400 | E51: ='0.1g PET, 2H'!AB61 -> 2890800
B52: Feedstock - PMA makeup | C52: ='0.1g PET, 2H'!Z62 -> 0 | D52: ='0.1g PET, 2H'!AA62 -> 0 | E52: ='0.1g PET, 2H'!AB62 -> 0
B53: Feedstock - H₂SO₄ makeup | C53: ='0.1g PET, 2H'!Z63 -> 0 | D53: ='0.1g PET, 2H'!AA63 -> 0 | E53: ='0.1g PET, 2H'!AB63 -> 0
B54: Feedstock - H₂O makeup | C54: ='0.1g PET, 2H'!Z64 -> 37076.244 | D54: ='0.1g PET, 2H'!AA64 -> 185381.22 | E54: ='0.1g PET, 2H'!AB64 -> 370762.44
B55: Feedstock Total | C55: ='0.1g PET, 2H'!Z65 -> 676556.24 | D55: ='0.1g PET, 2H'!AA65 -> 3382781.2 | E55: ='0.1g PET, 2H'!AB65 -> 5013562.4
B57: Utility - Electricity (H₂ Electrolysis) | C57: ='0.1g PET, 2H'!Z71 -> 566946.57 | D57: ='0.1g PET, 2H'!AA71 -> 2834732.9 | E57: ='0.1g PET, 2H'!AB71 -> 5669465.7
B58: Utility - Heat | C58: ='0.1g PET, 2H'!Z72 -> 269982.09 | D58: ='0.1g PET, 2H'!AA72 -> 1349910.4 | E58: ='0.1g PET, 2H'!AB72 -> 2699820.9
B59: Utility - Mechanical crushing | C59: ='0.1g PET, 2H'!Z73 -> 45552 | D59: ='0.1g PET, 2H'!AA73 -> 227760 | E59: ='0.1g PET, 2H'!AB73 -> 455520
B60: Utility Total | C60: ='0.1g PET, 2H'!Z74 -> 882480.66 | D60: ='0.1g PET, 2H'!AA74 -> 4412403.3 | E60: ='0.1g PET, 2H'!AB74 -> 8824806.6
B62: FA Distillation OPEX | C62: ='0.1g PET, 2H'!AE61 -> 1225310 | D62: ='0.1g PET, 2H'!AF61 -> 6126549.8 | E62: ='0.1g PET, 2H'!AG61 -> 12253100
B63: Maintenance (10% of CAPEX) | C63: ='0.1g PET, 2H'!AE71 -> 363031.69 | D63: ='0.1g PET, 2H'!AF71 -> 1815158.5 | E63: ='0.1g PET, 2H'!AG71 -> 3630316.9
B64: Operation (10% of CAPEX) | C64: ='0.1g PET, 2H'!AE72 -> 363031.69 | D64: ='0.1g PET, 2H'!AF72 -> 1815158.5 | E64: ='0.1g PET, 2H'!AG72 -> 3630316.9
B65: Operation Total | C65: =C62+C63+C64 -> 1951373.3 | D65: =D62+D63+D64 -> 9756866.7 | E65: =E62+E63+E64 -> 19513733
B67: Total OPEX | C67: =C55+C60+C65 -> 3510410.3 | D67: =D55+D60+D65 -> 17552051 | E67: =E55+E60+E65 -> 33352103
B69: 5. Revenue (Annual)
B71: Product | C71: 1 ton PET ($/y) | D71: 5 ton PET ($/y) | E71: 10 ton PET ($/y) | F71: Unit Price ($/kg)
B72: TPA | C72: ='0.1g PET, 2H'!Z80 -> 2845400.2 | D72: ='0.1g PET, 2H'!AA80 -> 14227001 | E72: ='0.1g PET, 2H'!AB80 -> 28454002 | F72: ='0.1g PET, 2H'!F40 -> 0.94
B73: FA | C73: ='0.1g PET, 2H'!Z81 -> 1192249.2 | D73: ='0.1g PET, 2H'!AA81 -> 5961245.9 | E73: ='0.1g PET, 2H'!AB81 -> 11922492 | F73: ='0.1g PET, 2H'!F41 -> 0.84
B74: H₂ | C74: ='0.1g PET, 2H'!Z82 -> 1491930.3 | D74: ='0.1g PET, 2H'!AA82 -> 7459651.6 | E74: ='0.1g PET, 2H'!AB82 -> 14919303 | F74: ='0.1g PET, 2H'!F42 -> 8
B75: Total Revenue | C75: ='0.1g PET, 2H'!Z83 -> 5529579.7 | D75: ='0.1g PET, 2H'!AA83 -> 27647899 | E75: ='0.1g PET, 2H'!AB83 -> 55295797
B77: 6. Profitability Analysis
C79: 1 ton PET ($/y) | D79: 5 ton PET ($/y) | E79: 10 ton PET ($/y)
B80: Total CAPEX (Annualized) | C80: =C45 -> 3755855.8 | D80: =D45 -> 10361231 | E80: =E45 -> 16211087
B81: Total OPEX | C81: =C67 -> 3510410.3 | D81: =D67 -> 17552051 | E81: =E67 -> 33352103
B82: Total Cost | C82: =C80+C81 -> 7266266.1 | D82: =D80+D81 -> 27913282 | E82: =E80+E81 -> 49563190
B83: Total Revenue | C83: =C75 -> 5529579.7 | D83: =D75 -> 27647899 | E83: =E75 -> 55295797
B84: Net Profit | C84: =C83-C82 -> -1736686.4 | D84: =D83-D82 -> -265383.71 | E84: =E83-E82 -> 5732607
B86: 7. MSP (Minimum Selling Price of TPA)
B88: Scale | C88: MSP ($/kg TPA)
B89: 1 ton PET / batch | C89: ='0.1g PET, 2H'!Z88 -> 1.5137278
B90: 5 ton PET / batch | C90: ='0.1g PET, 2H'!AA88 -> 0.95753431
B91: 10 ton PET / batch | C91: ='0.1g PET, 2H'!AB88 -> 0.75061889
B93: 8. Cost Breakdown (10 ton PET)
B95: Category | C95: Value ($/y) | D95: Portion (%)
B96: CAPEX (Annualized) | C96: =E45 -> 16211087 | D96: =C96/$C$100*100 -> 32.165411
B97: Feedstock Cost | C97: =E55+E43 -> 5849503.2 | D97: =C97/$C$100*100 -> 11.606357
B98: Utility Cost | C98: =E60 -> 8824806.6 | D98: =C98/$C$100*100 -> 17.509839
B99: Operation (Maint. + Oper. + Distillation) | C99: =E65 -> 19513733 | D99: =C99/$C$100*100 -> 38.718393
B100: Total | C100: =SUM(C96:C99) -> 50399131 | D100: =SUM(D96:D99) -> 100
B102: Revenue Breakdown (10 ton PET)
B103: Product | C103: Value ($/y) | D103: Portion (%)
B104: TPA | C104: =E72 -> 28454002 | D104: ='0.1g PET, 2H'!AC102 -> 51.457803
B105: FA | C105: =E73 -> 11922492 | D105: ='0.1g PET, 2H'!AC103 -> 21.561298
B106: H₂ | C106: =E74 -> 14919303 | D106: ='0.1g PET, 2H'!AC104 -> 26.980899
B108: 9. MSP Comparison with Other Methods
B110: Method | C110: MSP ($/kg TPA) | D110: Reference
B111: This study (10 ton PET) | C111: =C91 -> 0.75061889 | D111: -
B112: Glycolysis | C112: ='0.1g PET, 2H'!AE87 -> 0.96 | D112: ='0.1g PET, 2H'!AF87 -> ACS Sustainable Chem. Eng. 2023, 11, 965−978
B113: Methanolysis | C113: ='0.1g PET, 2H'!AE88 -> 1.05 | D113: ='0.1g PET, 2H'!AF88 -> ACS Sustainable Chem. Eng. 2023, 11, 965−978
B114: Enzymatic degradation | C114: ='0.1g PET, 2H'!AE89 -> 1.93 | D114: ='0.1g PET, 2H'!AF89 -> Joule 5, 2479–2503 (2021)
B115: Enzymatic degradation (2) | C115: ='0.1g PET, 2H'!AE90 -> 2.18 | D115: ='0.1g PET, 2H'!AF90 -> Green Chem., 2022, 24, 6531
B116: Solvent-based recycling | C116: ='0.1g PET, 2H'!AE92 -> 0.87 | D116: ='0.1g PET, 2H'!AF92 -> ACS Sustainable Chem. Eng. 2023, 11, 965−978
B117: Mechanical recycling | C117: ='0.1g PET, 2H'!AE93 -> 0.54 | D117: ='0.1g PET, 2H'!AF93 -> ACS Sustainable Chem. Eng. 2023, 11, 965−978
B118: Virgin TPA | C118: ='0.1g PET, 2H'!AE94 -> 1.14 | D118: ='0.1g PET, 2H'!AF94 -> Chem. Eng. Journal 481 (2024) 148278
B120: 10. Sensitivity Analysis (10 ton PET)
B122: DMSO Recovery (%) | C122: MSP ($/kg TPA)
B123: 0.99999 | C123: ='0.1g PET, 2H'!AA110 -> 0.75
B124: 0.9999 | C124: ='0.1g PET, 2H'!AA111 -> 1.61
B125: 0.999 | C125: ='0.1g PET, 2H'!AA112 -> 10.21
B126: 0.99 | C126: ='0.1g PET, 2H'!AA113 -> 96.15
...
